st_leaflet/__init__.py
st_leaflet/frontend/build/asset-manifest.json
st_leaflet/frontend/build/bootstrap.min.css
st_leaflet/frontend/build/index.html
st_leaflet/frontend/build/precache-manifest.157c78bc5fd788971abeb04e39e7185f.js
st_leaflet/frontend/build/service-worker.js
st_leaflet/frontend/build/static/js/2.75ac7c34.chunk.js
st_leaflet/frontend/build/static/js/2.75ac7c34.chunk.js.LICENSE.txt
st_leaflet/frontend/build/static/js/2.75ac7c34.chunk.js.map
st_leaflet/frontend/build/static/js/main.bbed1404.chunk.js
st_leaflet/frontend/build/static/js/main.bbed1404.chunk.js.map
st_leaflet/frontend/build/static/js/runtime-main.44d30fc2.js
st_leaflet/frontend/build/static/js/runtime-main.44d30fc2.js.map
streamlit_leaflet-0.1.0.dist-info/LICENSE
streamlit_leaflet-0.1.0.dist-info/METADATA
streamlit_leaflet-0.1.0.dist-info/WHEEL
streamlit_leaflet-0.1.0.dist-info/top_level.txt
streamlit_leaflet-0.1.0.dist-info/RECORD
